{
  "tick": 1084,
  "name": "MAIN",
  "hasHead": true,
    "canvas": {
      "resizable": false,
      "backgroundArea": "101010FF",
      "height": 370,
      "width": 550,
      "borderThickness": "0",
      "borderRadius": "2",
      "background": "252525FF",
      "foreground": "FFFFFFFF",
      "alarmBrushing": false
    },
    "widgets": [
      {
        "name": "Number#22",
        "type": "Tiles/Number",
        "properties": {
          "x": 95,
          "y": 140,
          "z": 0,
          "state": "Blue",
          "height": 25,
          "width": 65,
          "scale": 1,
          "visible": true,
          "text": "***",
          "borderThickness": "1",
          "borderRadius": "0",
          "borderBrush": "808080FF",
          "margin": "0",
          "background": "252525FF",
          "foreground": "FFE560FF",
          "hAlignment": "Center",
          "vAlignment": "Center"
        }
      },
      {
        "name": "Number#25",
        "type": "Tiles/Number",
        "properties": {
          "x": 95,
          "y": 175,
          "z": 0,
          "state": "Blue",
          "height": 25,
          "width": 65,
          "scale": 1,
          "visible": true,
          "text": "***",
          "borderThickness": "1",
          "borderRadius": "0",
          "borderBrush": "808080FF",
          "margin": "0",
          "background": "252525FF",
          "foreground": "FFE560FF",
          "hAlignment": "Center",
          "vAlignment": "Center"
        }
      },
    {
      "name": "Number#28",
      "type": "Tiles/Number",
      "properties": {
        "x": 95,
        "y": 210,
        "z": 0,
        "state": "Blue",
        "height": 25,
        "width": 65,
        "scale": 1,
        "visible": true,
        "text": "***",
        "borderThickness": "1",
        "borderRadius": "0",
        "borderBrush": "808080FF",
        "margin": "0",
        "background": "252525FF",
        "foreground": "FFE560FF",
        "hAlignment": "Center",
        "vAlignment": "Center"
      }
    },
    {
      "name": "Number#31",
      "type": "Tiles/Number",
      "properties": {
        "x": 95,
        "y": 245,
        "z": 0,
        "state": "Blue",
        "height": 25,
        "width": 65,
        "scale": 1,
        "visible": true,
        "text": "***",
        "borderThickness": "1",
        "borderRadius": "0",
        "borderBrush": "808080FF",
        "margin": "0",
        "background": "252525FF",
        "foreground": "FFE560FF",
        "hAlignment": "Center",
        "vAlignment": "Center"
      }
    },
    {
      "name": "Number#37",
      "type": "Tiles/Number",
      "properties": {
        "x": 95,
        "y": 105,
        "z": 0,
        "state": "Blue",
        "height": 25,
        "width": 65,
        "scale": 1,
        "visible": true,
        "text": "***",
        "borderThickness": "1",
        "borderRadius": "0",
        "borderBrush": "808080FF",
        "margin": "0",
        "background": "252525FF",
        "foreground": "FFE560FF",
        "hAlignment": "Center",
        "vAlignment": "Center"
      }
    },
    {
      "name": "Number#40",
      "type": "Tiles/Number",
      "properties": {
        "x": 95,
        "y": 70,
        "z": 0,
        "state": "Blue",
        "height": 25,
        "width": 65,
        "scale": 1,
        "visible": true,
        "text": "***",
        "borderThickness": "1",
        "borderRadius": "0",
        "borderBrush": "808080FF",
        "margin": "0",
        "background": "252525FF",
        "foreground": "FFE560FF",
        "hAlignment": "Center",
        "vAlignment": "Center"
      }
    },
    {
      "name": "Number#22_3",
      "type": "Tiles/Number",
      "properties": {
        "x": 235,
        "y": 140,
        "z": 0,
        "state": "Blue",
        "height": 25,
        "width": 65,
        "scale": 1,
        "visible": true,
        "text": "***",
        "borderThickness": "1",
        "borderRadius": "0",
        "borderBrush": "808080FF",
        "margin": "0",
        "background": "252525FF",
        "foreground": "FFE560FF",
        "hAlignment": "Center",
        "vAlignment": "Center"
      }
    },
    {
      "name": "Number#25_3",
      "type": "Tiles/Number",
      "properties": {
        "x": 235,
        "y": 175,
        "z": 0,
        "state": "Blue",
        "height": 25,
        "width": 65,
        "scale": 1,
        "visible": true,
        "text": "***",
        "borderThickness": "1",
        "borderRadius": "0",
        "borderBrush": "808080FF",
        "margin": "0",
        "background": "252525FF",
        "foreground": "FFE560FF",
        "hAlignment": "Center",
        "vAlignment": "Center"
      }
    },
    {
      "name": "Number#28_3",
      "type": "Tiles/Number",
      "properties": {
        "x": 235,
        "y": 210,
        "z": 0,
        "state": "Blue",
        "height": 25,
        "width": 65,
        "scale": 1,
        "visible": true,
        "text": "***",
        "borderThickness": "1",
        "borderRadius": "0",
        "borderBrush": "808080FF",
        "margin": "0",
        "background": "252525FF",
        "foreground": "FFE560FF",
        "hAlignment": "Center",
        "vAlignment": "Center"
      }
    },
    {
      "name": "Number#31_3",
      "type": "Tiles/Number",
      "properties": {
        "x": 235,
        "y": 245,
        "z": 0,
        "state": "Blue",
        "height": 25,
        "width": 65,
        "scale": 1,
        "visible": true,
        "text": "***",
        "borderThickness": "1",
        "borderRadius": "0",
        "borderBrush": "808080FF",
        "margin": "0",
        "background": "252525FF",
        "foreground": "FFE560FF",
        "hAlignment": "Center",
        "vAlignment": "Center"
      }
    },
    {
      "name": "Number#37_3",
      "type": "Tiles/Number",
      "properties": {
        "x": 235,
        "y": 105,
        "z": 0,
        "state": "Blue",
        "height": 25,
        "width": 65,
        "scale": 1,
        "visible": true,
        "text": "***",
        "borderThickness": "1",
        "borderRadius": "0",
        "borderBrush": "808080FF",
        "margin": "0",
        "background": "252525FF",
        "foreground": "FFE560FF",
        "hAlignment": "Center",
        "vAlignment": "Center"
      }
    },
    {
      "name": "Number#40_5",
      "type": "Tiles/Number",
      "properties": {
        "x": 235,
        "y": 70,
        "z": 0,
        "state": "Blue",
        "height": 25,
        "width": 65,
        "scale": 1,
        "visible": true,
        "text": "***",
        "borderThickness": "1",
        "borderRadius": "0",
        "borderBrush": "808080FF",
        "margin": "0",
        "background": "252525FF",
        "foreground": "FFE560FF",
        "hAlignment": "Center",
        "vAlignment": "Center"
      }
    },
    {
      "name": "Number#37_4",
      "type": "Tiles/Number",
      "properties": {
        "x": 95,
        "y": 315,
        "z": 0,
        "state": "Blue",
        "height": 25,
        "width": 65,
        "scale": 1,
        "visible": true,
        "text": "***",
        "borderThickness": "1",
        "borderRadius": "0",
        "borderBrush": "808080FF",
        "margin": "0",
        "background": "252525FF",
        "foreground": "FFE560FF",
        "hAlignment": "Center",
        "vAlignment": "Center"
      }
    },
    {
      "name": "Number#37_5",
      "type": "Tiles/Number",
      "properties": {
        "x": 165,
        "y": 315,
        "z": 0,
        "state": "Blue",
        "height": 25,
        "width": 65,
        "scale": 1,
        "visible": true,
        "text": "***",
        "borderThickness": "1",
        "borderRadius": "0",
        "borderBrush": "808080FF",
        "margin": "0",
        "background": "252525FF",
        "foreground": "FFE560FF",
        "hAlignment": "Center",
        "vAlignment": "Center"
      }
    },
    {
      "name": "Number#37_6",
      "type": "Tiles/Number",
      "properties": {
        "x": 235,
        "y": 315,
        "z": 0,
        "state": "Blue",
        "height": 25,
        "width": 65,
        "scale": 1,
        "visible": true,
        "text": "***",
        "borderThickness": "1",
        "borderRadius": "0",
        "borderBrush": "808080FF",
        "margin": "0",
        "background": "252525FF",
        "foreground": "FFE560FF",
        "hAlignment": "Center",
        "vAlignment": "Center"
      }
    },
    {
      "name": "unnamed#7",
      "type": "Tiles/Text",
      "properties": {
        "x": 95,
        "y": 290,
        "z": 0,
        "state": "Green",
        "height": 25,
        "width": 65,
        "scale": 1,
        "visible": true,
        "text": "AB",
        "borderThickness": "0",
        "borderRadius": "0",
        "borderBrush": "FFFFFFFF",
        "margin": "5",
        "fontSize": 12,
        "background": "252525FF",
        "foreground": "FFFFFFFF",
        "hAlignment": "Center",
        "vAlignment": "Center"
      }
    },
    {
      "name": "unnamed#7_2",
      "type": "Tiles/Text",
      "properties": {
        "x": 165,
        "y": 290,
        "z": 0,
        "state": "Green",
        "height": 25,
        "width": 65,
        "scale": 1,
        "visible": true,
        "text": "BC",
        "borderThickness": "0",
        "borderRadius": "0",
        "borderBrush": "FFFFFFFF",
        "margin": "5",
        "fontSize": 12,
        "background": "252525FF",
        "foreground": "FFFFFFFF",
        "hAlignment": "Center",
        "vAlignment": "Center"
      }
    },
    {
      "name": "unnamed#7_3",
      "type": "Tiles/Text",
      "properties": {
        "x": 235,
        "y": 290,
        "z": 0,
        "state": "Green",
        "height": 25,
        "width": 65,
        "scale": 1,
        "visible": true,
        "text": "CA",
        "borderThickness": "0",
        "borderRadius": "0",
        "borderBrush": "FFFFFFFF",
        "margin": "5",
        "fontSize": 12,
        "background": "252525FF",
        "foreground": "FFFFFFFF",
        "hAlignment": "Center",
        "vAlignment": "Center"
      }
    },
    {
      "name": "unnamed#5_3",
      "type": "Tiles/Text",
      "properties": {
        "x": 20,
        "y": 315,
        "z": -1,
        "state": "Green",
        "height": 25,
        "width": 60,
        "scale": 1,
        "visible": true,
        "text": "U, кВ",
        "borderThickness": "0",
        "borderRadius": "0",
        "borderBrush": "FFFFFFFF",
        "margin": "5",
        "fontSize": 13,
        "background": "252525FF",
        "foreground": "FFFFFFFF",
        "vAlignment": "Center"
      }
    },
    {
      "name": "unnamed#19_3",
      "type": "Primitives/Line",
      "properties": {
        "x": 105,
        "y": 285,
        "z": 0,
        "state": "Green",
        "height": 0,
        "width": 420,
        "scale": 1,
        "visible": true,
        "thickness": 2,
        "x2": 420,
        "y1": 0,
        "y2": 0,
        "foreground": "D3D3D3FF"
      }
    },
    {
      "name": "Number#22_4",
      "type": "Tiles/Number",
      "properties": {
        "x": 320,
        "y": 140,
        "z": 0,
        "state": "Blue",
        "height": 25,
        "width": 65,
        "scale": 1,
        "visible": true,
        "text": "***",
        "borderThickness": "1",
        "borderRadius": "0",
        "borderBrush": "808080FF",
        "margin": "0",
        "background": "252525FF",
        "foreground": "FFE560FF",
        "hAlignment": "Center",
        "vAlignment": "Center"
      }
    },
    {
      "name": "Number#25_4",
      "type": "Tiles/Number",
      "properties": {
        "x": 320,
        "y": 175,
        "z": 0,
        "state": "Blue",
        "height": 25,
        "width": 65,
        "scale": 1,
        "visible": true,
        "text": "***",
        "borderThickness": "1",
        "borderRadius": "0",
        "borderBrush": "808080FF",
        "margin": "0",
        "background": "252525FF",
        "foreground": "FFE560FF",
        "hAlignment": "Center",
        "vAlignment": "Center"
      }
    },
    {
      "name": "Number#28_4",
      "type": "Tiles/Number",
      "properties": {
        "x": 320,
        "y": 210,
        "z": 0,
        "state": "Blue",
        "height": 25,
        "width": 65,
        "scale": 1,
        "visible": true,
        "text": "***",
        "borderThickness": "1",
        "borderRadius": "0",
        "borderBrush": "808080FF",
        "margin": "0",
        "background": "252525FF",
        "foreground": "FFE560FF",
        "hAlignment": "Center",
        "vAlignment": "Center"
      }
    },
    {
      "name": "Number#31_4",
      "type": "Tiles/Number",
      "properties": {
        "x": 320,
        "y": 245,
        "z": 0,
        "state": "Blue",
        "height": 25,
        "width": 65,
        "scale": 1,
        "visible": true,
        "text": "***",
        "borderThickness": "1",
        "borderRadius": "0",
        "borderBrush": "808080FF",
        "margin": "0",
        "background": "252525FF",
        "foreground": "FFE560FF",
        "hAlignment": "Center",
        "vAlignment": "Center"
      }
    },
    {
      "name": "Number#37_7",
      "type": "Tiles/Number",
      "properties": {
        "x": 320,
        "y": 105,
        "z": 0,
        "state": "Blue",
        "height": 25,
        "width": 65,
        "scale": 1,
        "visible": true,
        "text": "***",
        "borderThickness": "1",
        "borderRadius": "0",
        "borderBrush": "808080FF",
        "margin": "0",
        "background": "252525FF",
        "foreground": "FFE560FF",
        "hAlignment": "Center",
        "vAlignment": "Center"
      }
    },
    {
      "name": "Number#40_7",
      "type": "Tiles/Number",
      "properties": {
        "x": 320,
        "y": 70,
        "z": 0,
        "state": "Blue",
        "height": 25,
        "width": 65,
        "scale": 1,
        "visible": true,
        "text": "***",
        "borderThickness": "1",
        "borderRadius": "0",
        "borderBrush": "808080FF",
        "margin": "0",
        "background": "252525FF",
        "foreground": "FFE560FF",
        "hAlignment": "Center",
        "vAlignment": "Center"
      }
    },
    {
      "name": "Number#22_5",
      "type": "Tiles/Number",
      "properties": {
        "x": 390,
        "y": 140,
        "z": 0,
        "state": "Blue",
        "height": 25,
        "width": 65,
        "scale": 1,
        "visible": true,
        "text": "***",
        "borderThickness": "1",
        "borderRadius": "0",
        "borderBrush": "808080FF",
        "margin": "0",
        "background": "252525FF",
        "foreground": "FFE560FF",
        "hAlignment": "Center",
        "vAlignment": "Center"
      }
    },
    {
      "name": "Number#25_5",
      "type": "Tiles/Number",
      "properties": {
        "x": 390,
        "y": 175,
        "z": 0,
        "state": "Blue",
        "height": 25,
        "width": 65,
        "scale": 1,
        "visible": true,
        "text": "***",
        "borderThickness": "1",
        "borderRadius": "0",
        "borderBrush": "808080FF",
        "margin": "0",
        "background": "252525FF",
        "foreground": "FFE560FF",
        "hAlignment": "Center",
        "vAlignment": "Center"
      }
    },
    {
      "name": "Number#28_5",
      "type": "Tiles/Number",
      "properties": {
        "x": 390,
        "y": 210,
        "z": 0,
        "state": "Blue",
        "height": 25,
        "width": 65,
        "scale": 1,
        "visible": true,
        "text": "***",
        "borderThickness": "1",
        "borderRadius": "0",
        "borderBrush": "808080FF",
        "margin": "0",
        "background": "252525FF",
        "foreground": "FFE560FF",
        "hAlignment": "Center",
        "vAlignment": "Center"
      }
    },
    {
      "name": "Number#31_5",
      "type": "Tiles/Number",
      "properties": {
        "x": 390,
        "y": 245,
        "z": 0,
        "state": "Blue",
        "height": 25,
        "width": 65,
        "scale": 1,
        "visible": true,
        "text": "***",
        "borderThickness": "1",
        "borderRadius": "0",
        "borderBrush": "808080FF",
        "margin": "0",
        "background": "252525FF",
        "foreground": "FFE560FF",
        "hAlignment": "Center",
        "vAlignment": "Center"
      }
    },
    {
      "name": "Number#37_8",
      "type": "Tiles/Number",
      "properties": {
        "x": 390,
        "y": 105,
        "z": 0,
        "state": "Blue",
        "height": 25,
        "width": 65,
        "scale": 1,
        "visible": true,
        "text": "***",
        "borderThickness": "1",
        "borderRadius": "0",
        "borderBrush": "808080FF",
        "margin": "0",
        "background": "252525FF",
        "foreground": "FFE560FF",
        "hAlignment": "Center",
        "vAlignment": "Center"
      }
    },
    {
      "name": "Number#40_9",
      "type": "Tiles/Number",
      "properties": {
        "x": 390,
        "y": 70,
        "z": 0,
        "state": "Blue",
        "height": 25,
        "width": 65,
        "scale": 1,
        "visible": true,
        "text": "***",
        "borderThickness": "1",
        "borderRadius": "0",
        "borderBrush": "808080FF",
        "margin": "0",
        "background": "252525FF",
        "foreground": "FFE560FF",
        "hAlignment": "Center",
        "vAlignment": "Center"
      }
    },
    {
      "name": "Number#22_6",
      "type": "Tiles/Number",
      "properties": {
        "x": 460,
        "y": 140,
        "z": 0,
        "state": "Blue",
        "height": 25,
        "width": 65,
        "scale": 1,
        "visible": true,
        "text": "***",
        "borderThickness": "1",
        "borderRadius": "0",
        "borderBrush": "808080FF",
        "margin": "0",
        "background": "252525FF",
        "foreground": "FFE560FF",
        "hAlignment": "Center",
        "vAlignment": "Center"
      }
    },
    {
      "name": "Number#25_6",
      "type": "Tiles/Number",
      "properties": {
        "x": 460,
        "y": 175,
        "z": 0,
        "state": "Blue",
        "height": 25,
        "width": 65,
        "scale": 1,
        "visible": true,
        "text": "***",
        "borderThickness": "1",
        "borderRadius": "0",
        "borderBrush": "808080FF",
        "margin": "0",
        "background": "252525FF",
        "foreground": "FFE560FF",
        "hAlignment": "Center",
        "vAlignment": "Center"
      }
    },
    {
      "name": "Number#28_6",
      "type": "Tiles/Number",
      "properties": {
        "x": 460,
        "y": 210,
        "z": 0,
        "state": "Blue",
        "height": 25,
        "width": 65,
        "scale": 1,
        "visible": true,
        "text": "***",
        "borderThickness": "1",
        "borderRadius": "0",
        "borderBrush": "808080FF",
        "margin": "0",
        "background": "252525FF",
        "foreground": "FFE560FF",
        "hAlignment": "Center",
        "vAlignment": "Center"
      }
    },
    {
      "name": "Number#31_6",
      "type": "Tiles/Number",
      "properties": {
        "x": 460,
        "y": 245,
        "z": 0,
        "state": "Blue",
        "height": 25,
        "width": 65,
        "scale": 1,
        "visible": true,
        "text": "***",
        "borderThickness": "1",
        "borderRadius": "0",
        "borderBrush": "808080FF",
        "margin": "0",
        "background": "252525FF",
        "foreground": "FFE560FF",
        "hAlignment": "Center",
        "vAlignment": "Center"
      }
    },
    {
      "name": "Number#37_9",
      "type": "Tiles/Number",
      "properties": {
        "x": 460,
        "y": 105,
        "z": 0,
        "state": "Blue",
        "height": 25,
        "width": 65,
        "scale": 1,
        "visible": true,
        "text": "***",
        "borderThickness": "1",
        "borderRadius": "0",
        "borderBrush": "808080FF",
        "margin": "0",
        "background": "252525FF",
        "foreground": "FFE560FF",
        "hAlignment": "Center",
        "vAlignment": "Center"
      }
    },
    {
      "name": "Number#40_11",
      "type": "Tiles/Number",
      "properties": {
        "x": 460,
        "y": 70,
        "z": 0,
        "state": "Blue",
        "height": 25,
        "width": 65,
        "scale": 1,
        "visible": true,
        "text": "***",
        "borderThickness": "1",
        "borderRadius": "0",
        "borderBrush": "808080FF",
        "margin": "0",
        "background": "252525FF",
        "foreground": "FFE560FF",
        "hAlignment": "Center",
        "vAlignment": "Center"
      }
    },
    {
      "name": "Number#37_10",
      "type": "Tiles/Number",
      "properties": {
        "x": 320,
        "y": 315,
        "z": 0,
        "state": "Blue",
        "height": 25,
        "width": 65,
        "scale": 1,
        "visible": true,
        "text": "***",
        "borderThickness": "1",
        "borderRadius": "0",
        "borderBrush": "808080FF",
        "margin": "0",
        "background": "252525FF",
        "foreground": "FFE560FF",
        "hAlignment": "Center",
        "vAlignment": "Center"
      }
    },
    {
      "name": "Number#37_11",
      "type": "Tiles/Number",
      "properties": {
        "x": 390,
        "y": 315,
        "z": 0,
        "state": "Blue",
        "height": 25,
        "width": 65,
        "scale": 1,
        "visible": true,
        "text": "***",
        "borderThickness": "1",
        "borderRadius": "0",
        "borderBrush": "808080FF",
        "margin": "0",
        "background": "252525FF",
        "foreground": "FFE560FF",
        "hAlignment": "Center",
        "vAlignment": "Center"
      }
    },
    {
      "name": "Number#37_12",
      "type": "Tiles/Number",
      "properties": {
        "x": 460,
        "y": 315,
        "z": 0,
        "state": "Blue",
        "height": 25,
        "width": 65,
        "scale": 1,
        "visible": true,
        "text": "***",
        "borderThickness": "1",
        "borderRadius": "0",
        "borderBrush": "808080FF",
        "margin": "0",
        "background": "252525FF",
        "foreground": "FFE560FF",
        "hAlignment": "Center",
        "vAlignment": "Center"
      }
    },
    {
      "name": "unnamed#11",
      "type": "Tiles/Text",
      "properties": {
        "x": 180,
        "y": 40,
        "z": 0,
        "state": "Green",
        "height": 25,
        "width": 25,
        "scale": 1,
        "visible": true,
        "text": " B",
        "borderThickness": "0",
        "borderRadius": "0",
        "borderBrush": "FFFFFFFF",
        "margin": "5",
        "fontSize": 13,
        "background": "252525FF",
        "foreground": "00FF00FF",
        "vAlignment": "Center"
      }
    },
    {
      "name": "unnamed#12_2",
      "type": "Tiles/Text",
      "properties": {
        "x": 250,
        "y": 40,
        "z": 0,
        "state": "Green",
        "height": 25,
        "width": 25,
        "scale": 1,
        "visible": true,
        "text": " C",
        "borderThickness": "0",
        "borderRadius": "0",
        "borderBrush": "FFFFFFFF",
        "margin": "5",
        "fontSize": 13,
        "background": "252525FF",
        "foreground": "FF0000FF",
        "vAlignment": "Center"
      }
    },
    {
      "name": "Line",
      "type": "Primitives/Line",
      "properties": {
        "x": 310,
        "y": 35,
        "z": 0,
        "state": "Green",
        "height": 300,
        "width": 0,
        "scale": 1,
        "visible": true,
        "thickness": 2,
        "x2": 0,
        "y1": 0,
        "y2": 300,
        "foreground": "FFFFFFFF"
      }
    },
    {
      "name": "unnamed#13",
      "type": "Tiles/Text",
      "properties": {
        "x": 335,
        "y": 40,
        "z": 0,
        "state": "Green",
        "height": 25,
        "width": 25,
        "scale": 1,
        "visible": true,
        "text": " A",
        "borderThickness": "0",
        "borderRadius": "0",
        "borderBrush": "FFFFFFFF",
        "margin": "5",
        "fontSize": 13,
        "background": "252525FF",
        "foreground": "FFFF00FF",
        "vAlignment": "Center"
      }
    },
    {
      "name": "unnamed#14",
      "type": "Tiles/Text",
      "properties": {
        "x": 405,
        "y": 40,
        "z": 0,
        "state": "Green",
        "height": 25,
        "width": 25,
        "scale": 1,
        "visible": true,
        "text": " B",
        "borderThickness": "0",
        "borderRadius": "0",
        "borderBrush": "FFFFFFFF",
        "margin": "5",
        "fontSize": 13,
        "background": "252525FF",
        "foreground": "00FF00FF",
        "vAlignment": "Center"
      }
    },
    {
      "name": "unnamed#15",
      "type": "Tiles/Text",
      "properties": {
        "x": 475,
        "y": 40,
        "z": 0,
        "state": "Green",
        "height": 25,
        "width": 25,
        "scale": 1,
        "visible": true,
        "text": " C",
        "borderThickness": "0",
        "borderRadius": "0",
        "borderBrush": "FFFFFFFF",
        "margin": "5",
        "fontSize": 13,
        "background": "252525FF",
        "foreground": "FF0000FF",
        "vAlignment": "Center"
      }
    },
    {
      "name": "unnamed#6_2",
      "type": "Tiles/Text",
      "properties": {
        "x": 20,
        "y": 70,
        "z": -1,
        "state": "Green",
        "height": 25,
        "width": 60,
        "scale": 1,
        "visible": true,
        "text": "I, A",
        "borderThickness": "0",
        "borderRadius": "0",
        "borderBrush": "FFFFFFFF",
        "margin": "5",
        "fontSize": 13,
        "background": "252525FF",
        "foreground": "FFFFFFFF",
        "vAlignment": "Center"
      }
    },
    {
      "name": "unnamed#5_4",
      "type": "Tiles/Text",
      "properties": {
        "x": 20,
        "y": 105,
        "z": -1,
        "state": "Green",
        "height": 25,
        "width": 60,
        "scale": 1,
        "visible": true,
        "text": "U, кВ",
        "borderThickness": "0",
        "borderRadius": "0",
        "borderBrush": "FFFFFFFF",
        "margin": "5",
        "fontSize": 13,
        "background": "252525FF",
        "foreground": "FFFFFFFF",
        "vAlignment": "Center"
      }
    },
    {
      "name": "unnamed_3",
      "type": "Tiles/Text",
      "properties": {
        "x": 20,
        "y": 140,
        "z": -1,
        "state": "Green",
        "height": 25,
        "width": 60,
        "scale": 1,
        "visible": true,
        "text": "S, МВА",
        "borderThickness": "0",
        "borderRadius": "0",
        "borderBrush": "FFFFFFFF",
        "margin": "5",
        "fontSize": 13,
        "background": "252525FF",
        "foreground": "FFFFFFFF",
        "vAlignment": "Center"
      }
    },
    {
      "name": "unnamed#2_3",
      "type": "Tiles/Text",
      "properties": {
        "x": 20,
        "y": 175,
        "z": -1,
        "state": "Green",
        "height": 25,
        "width": 60,
        "scale": 1,
        "visible": true,
        "text": "Р, МВт",
        "borderThickness": "0",
        "borderRadius": "0",
        "borderBrush": "FFFFFFFF",
        "margin": "5",
        "fontSize": 13,
        "background": "252525FF",
        "foreground": "FFFFFFFF",
        "vAlignment": "Center"
      }
    },
    {
      "name": "unnamed#3_3",
      "type": "Tiles/Text",
      "properties": {
        "x": 20,
        "y": 210,
        "z": -1,
        "state": "Green",
        "height": 25,
        "width": 60,
        "scale": 1,
        "visible": true,
        "text": "Q, МВАр",
        "borderThickness": "0",
        "borderRadius": "0",
        "borderBrush": "FFFFFFFF",
        "margin": "5",
        "fontSize": 13,
        "background": "252525FF",
        "foreground": "FFFFFFFF",
        "vAlignment": "Center"
      }
    },
    {
      "name": "unnamed#4_3",
      "type": "Tiles/Text",
      "properties": {
        "x": 20,
        "y": 245,
        "z": -1,
        "state": "Green",
        "height": 25,
        "width": 60,
        "scale": 1,
        "visible": true,
        "text": "cos ⱷ",
        "borderThickness": "0",
        "borderRadius": "0",
        "borderBrush": "FFFFFFFF",
        "margin": "5",
        "fontSize": 13,
        "background": "252525FF",
        "foreground": "FFFFFFFF",
        "vAlignment": "Center"
      }
    },
    {
      "name": "Number#40_3",
      "type": "Tiles/Number",
      "properties": {
        "x": 165,
        "y": 70,
        "z": 0,
        "state": "Blue",
        "height": 25,
        "width": 65,
        "scale": 1,
        "visible": true,
        "text": "***",
        "borderThickness": "1",
        "borderRadius": "0",
        "borderBrush": "808080FF",
        "margin": "0",
        "background": "252525FF",
        "foreground": "FFE560FF",
        "hAlignment": "Center",
        "vAlignment": "Center"
      }
    },
    {
      "name": "Number#37_2",
      "type": "Tiles/Number",
      "properties": {
        "x": 165,
        "y": 105,
        "z": 0,
        "state": "Blue",
        "height": 25,
        "width": 65,
        "scale": 1,
        "visible": true,
        "text": "***",
        "borderThickness": "1",
        "borderRadius": "0",
        "borderBrush": "808080FF",
        "margin": "0",
        "background": "252525FF",
        "foreground": "FFE560FF",
        "hAlignment": "Center",
        "vAlignment": "Center"
      }
    },
    {
      "name": "Number#31_2",
      "type": "Tiles/Number",
      "properties": {
        "x": 165,
        "y": 245,
        "z": 0,
        "state": "Blue",
        "height": 25,
        "width": 65,
        "scale": 1,
        "visible": true,
        "text": "***",
        "borderThickness": "1",
        "borderRadius": "0",
        "borderBrush": "808080FF",
        "margin": "0",
        "background": "252525FF",
        "foreground": "FFE560FF",
        "hAlignment": "Center",
        "vAlignment": "Center"
      }
    },
    {
      "name": "Number#28_2",
      "type": "Tiles/Number",
      "properties": {
        "x": 165,
        "y": 210,
        "z": 0,
        "state": "Blue",
        "height": 25,
        "width": 65,
        "scale": 1,
        "visible": true,
        "text": "***",
        "borderThickness": "1",
        "borderRadius": "0",
        "borderBrush": "808080FF",
        "margin": "0",
        "background": "252525FF",
        "foreground": "FFE560FF",
        "hAlignment": "Center",
        "vAlignment": "Center"
      }
    },
    {
      "name": "Number#25_2",
      "type": "Tiles/Number",
      "properties": {
        "x": 165,
        "y": 175,
        "z": 0,
        "state": "Blue",
        "height": 25,
        "width": 65,
        "scale": 1,
        "visible": true,
        "text": "***",
        "borderThickness": "1",
        "borderRadius": "0",
        "borderBrush": "808080FF",
        "margin": "0",
        "background": "252525FF",
        "foreground": "FFE560FF",
        "hAlignment": "Center",
        "vAlignment": "Center"
      }
    },
    {
      "name": "Number#22_2",
      "type": "Tiles/Number",
      "properties": {
        "x": 165,
        "y": 140,
        "z": 0,
        "state": "Blue",
        "height": 25,
        "width": 65,
        "scale": 1,
        "visible": true,
        "text": "***",
        "borderThickness": "1",
        "borderRadius": "0",
        "borderBrush": "808080FF",
        "margin": "0",
        "background": "252525FF",
        "foreground": "FFE560FF",
        "hAlignment": "Center",
        "vAlignment": "Center"
      }
    },
    {
      "name": "unnamed#7_7",
      "type": "Tiles/Text",
      "properties": {
        "x": 320,
        "y": 290,
        "z": 0,
        "state": "Green",
        "height": 25,
        "width": 65,
        "scale": 1,
        "visible": true,
        "text": "AB",
        "borderThickness": "0",
        "borderRadius": "0",
        "borderBrush": "FFFFFFFF",
        "margin": "5",
        "fontSize": 12,
        "background": "252525FF",
        "foreground": "FFFFFFFF",
        "hAlignment": "Center",
        "vAlignment": "Center"
      }
    },
    {
      "name": "unnamed#7_8",
      "type": "Tiles/Text",
      "properties": {
        "x": 390,
        "y": 290,
        "z": 0,
        "state": "Green",
        "height": 25,
        "width": 65,
        "scale": 1,
        "visible": true,
        "text": "BC",
        "borderThickness": "0",
        "borderRadius": "0",
        "borderBrush": "FFFFFFFF",
        "margin": "5",
        "fontSize": 12,
        "background": "252525FF",
        "foreground": "FFFFFFFF",
        "hAlignment": "Center",
        "vAlignment": "Center"
      }
    },
    {
      "name": "unnamed#7_9",
      "type": "Tiles/Text",
      "properties": {
        "x": 460,
        "y": 290,
        "z": 0,
        "state": "Green",
        "height": 25,
        "width": 65,
        "scale": 1,
        "visible": true,
        "text": "CA",
        "borderThickness": "0",
        "borderRadius": "0",
        "borderBrush": "FFFFFFFF",
        "margin": "5",
        "fontSize": 12,
        "background": "252525FF",
        "foreground": "FFFFFFFF",
        "hAlignment": "Center",
        "vAlignment": "Center"
      }
    },
    {
      "name": "Text#9",
      "type": "Tiles/Text",
      "properties": {
        "x": 175,
        "y": 10,
        "z": 0,
        "state": "Green",
        "height": 35,
        "width": 53,
        "scale": 1,
        "visible": true,
        "text": "ВН",
        "borderThickness": "0",
        "borderRadius": "0",
        "borderBrush": "FFFFFFFF",
        "margin": "5",
        "fontSize": 15,
        "background": "252525FF",
        "foreground": "FFFFFFFF",
        "hAlignment": "Center",
        "vAlignment": "Center"
      }
    },
    {
      "name": "Text#10",
      "type": "Tiles/Text",
      "properties": {
        "x": 405,
        "y": 10,
        "z": 0,
        "state": "Green",
        "height": 35,
        "width": 53,
        "scale": 1,
        "visible": true,
        "text": "НН",
        "borderThickness": "0",
        "borderRadius": "0",
        "borderBrush": "FFFFFFFF",
        "margin": "5",
        "fontSize": 15,
        "background": "252525FF",
        "foreground": "FFFFFFFF",
        "hAlignment": "Center",
        "vAlignment": "Center"
      }
    },
    {
      "name": "unnamed#10",
      "type": "Tiles/Text",
      "properties": {
        "x": 110,
        "y": 40,
        "z": 0,
        "state": "Green",
        "height": 25,
        "width": 25,
        "scale": 1,
        "visible": true,
        "text": " A",
        "borderThickness": "0",
        "borderRadius": "0",
        "borderBrush": "FFFFFFFF",
        "margin": "5",
        "fontSize": 13,
        "background": "252525FF",
        "foreground": "FFFF00FF",
        "vAlignment": "Center"
      }
    }
  ]
}